Procesador_completo/RegisterFile.v
// Banco de Registros (Register File) 
// Universidad del Valle de Guatemala
// Curso: Arquitectura de Computadores
// Autor: Samuel Tortola - 22094, Alan Gomez - 22115
// Fecha: 1/10/2025

// El Banco de Registros es un componente esencial en la arquitectura de computadores que almacena
// un conjunto de registros utilizados para operaciones de lectura y escritura durante la ejecución

module RegisterFile (
    input  clk,                     // Reloj del sistema
    input reset,                // Señal de reinicio    
    input RegWrite,               // Señal de control para habilitar la escritura
    input [4:0] read_reg1,        // Dirección del primer registro a leer
    input [4:0] read_reg2,        // Dirección del segundo registro a leer
    input [4:0] write_reg,        // Dirección del registro a escribir
    input [31:0] write_data,      // Datos a escribir en el registro
    output [31:0] read_data1,      // Datos leídos del primer registro
    output [31:0] read_data2       // Datos leídos del segundo registro
);

    // Definición del banco de registros (32 registros de 32 bits cada uno)
    reg [31:0] registers [0:31];

    // Lectura de registros
    assign read_data1 = registers[read_reg1];
    assign read_data2 = registers[read_reg2];
 

    // Escritura de registros 
    integer i;
    always @(posedge clk or posedge reset) begin

         if (reset) begin
            for (i = 0; i < 32; i = i + 1) begin
                registers[i] <= 32'b0;
            end
        end

        else if (RegWrite && (write_reg != 5'd0)) begin  // Evita escribir en registro $0
            registers[write_reg] <= write_data;
        end

       
    end
endmodule

ALU_control_&_Banco_registros/Testbench_register.v
module testbench_banco;

    // ================================================
    // 1. DECLARACIÓN DE SEÑALES
    // ================================================
    // Señales para conectar al DUT (Design Under Test)
    reg  clk;
    reg  reset;
    reg  RegWrite;
    reg  [4:0] read_reg1;
    reg  [4:0] read_reg2;
    reg  [4:0] write_reg;
    reg  [31:0] write_data;
    wire [31:0] read_data1;
    wire [31:0] read_data2;


     // ================================================
    // 2. INSTANCIACIÓN DEL DISEÑO BAJO PRUEBA (DUT)
    // ================================================
    RegisterFile dut (
        .clk(clk),
        .reset(reset),
        .RegWrite(RegWrite),
        .read_reg1(read_reg1),
        .read_reg2(read_reg2),
        .write_reg(write_reg),
        .write_data(write_data),
        .read_data1(read_data1),
        .read_data2(read_data2)
    );


     // ================================================
    // 3. GENERACIÓN DE ESTÍMULOS Y MONITOREO
    // ================================================

    // Generación de reloj
    initial begin
        clk = 0;
        forever #5 clk = ~clk; // Periodo de 10 unidades de tiempo
    end

    initial begin
        // Inicialización de señales
        reset = 1;
        RegWrite = 0;
        read_reg1 = 5'd0;
        read_reg2 = 5'd0;
        write_reg = 5'd0;
        write_data = 32'd0;

        // Liberar el reset después de un tiempo
        #10;
        reset = 0;

        // Escritura y lectura en el registro 5, lectura en el registro 0
        #10;
        RegWrite = 1;
        write_reg = 5'd5;
        write_data = 32'hA5A5A5A5;
        $display("Escritura en R5 = 0x%h", write_data);

        #10;
        RegWrite = 0;
        read_reg1 = 5'd5;
        read_reg2 = 5'd0;
        $display("Lectura: R5 = 0x%h, R0 = 0x%h", read_data1, read_data2);
        $display("");



        // Escritura  y lectura en el registro 12, y lectura en el registro 0
        #10;
        RegWrite = 1;
        write_reg = 5'd12;
        write_data = 32'hAAAAAAAA;
        $display("Escritura en R12 = 0x%h", write_data);

        #10;
        RegWrite = 0;
        read_reg1 = 5'd12;
        read_reg2 = 5'd0;
        $display("Lectura: R12 = 0x%h, R0 = 0x%h", read_data1, read_data2);
        $display("");


        // Intento de escritura en el registro 0 (debe ser ignorado), lectura en el registro 0 y 5
        #10;
        RegWrite = 1;
        write_reg = 5'd0;   
        write_data = 32'hFFFFFFFF;
        $display("Intento de escritura en R0 = 0x%h", write_data);

        #10;
        RegWrite = 0;
        read_reg1 = 5'd0;
        read_reg2 = 5'd5;
        $display("Lectura: R0 = 0x%h, R5 = 0x%h", read_data1, read_data2);
        $display("");

        // Escritura y lectura en el registro 31, lectura en el registro 12
        #10;
        RegWrite = 1;
        write_reg = 5'd31;
        write_data = 32'h12345678;
        $display("Escritura en R31 = 0x%h", write_data);

        #10;
        RegWrite = 0;
        read_reg1 = 5'd31;
        read_reg2 = 5'd12;
        $display("Lectura: R31 = 0x%h, R12 = 0x%h", read_data1, read_data2);
        $display("");


        //Lectura en registros no escritos (R1 y R2)
        #10;
        read_reg1 = 5'd1;
        read_reg2 = 5'd2;
        $display("Lectura: R1 = 0x%h, R2 = 0x%h", read_data1, read_data2);
        $display("");





        // Finalizar la simulación
        #20;
        $finish;
    end

    initial begin
        $dumpfile("RegisterFile.vcd");
        $dumpvars(0, testbench_banco);
    end



endmodule

ALU_control_&_Banco_registros/RegisterFile.vcd
$date
	Sun Oct 26 14:50:40 2025
$end
$version
	Icarus Verilog
$end
$timescale
	1s
$end
$scope module testbench_banco $end
$var wire 32 ! read_data2 [31:0] $end
$var wire 32 " read_data1 [31:0] $end
$var reg 1 # RegWrite $end
$var reg 1 $ clk $end
$var reg 5 % read_reg1 [4:0] $end
$var reg 5 & read_reg2 [4:0] $end
$var reg 1 ' reset $end
$var reg 32 ( write_data [31:0] $end
$var reg 5 ) write_reg [4:0] $end
$scope module dut $end
$var wire 1 # RegWrite $end
$var wire 1 $ clk $end
$var wire 32 * read_data1 [31:0] $end
$var wire 32 + read_data2 [31:0] $end
$var wire 5 , read_reg1 [4:0] $end
$var wire 5 - read_reg2 [4:0] $end
$var wire 1 ' reset $end
$var wire 32 . write_data [31:0] $end
$var wire 5 / write_reg [4:0] $end
$var integer 32 0 i [31:0] $end
$upscope $end
$upscope $end
$enddefinitions $end
$comment Show the parameter values. $end
$dumpall
$end
#0
$dumpvars
b100000 0
b0 /
b0 .
b0 -
b0 ,
b0 +
b0 *
b0 )
b0 (
1'
b0 &
b0 %
0$
0#
b0 "
b0 !
$end
#5
b100000 0
1$
#10
0$
0'
#15
1$
#20
0$
b10100101101001011010010110100101 (
b10100101101001011010010110100101 .
b101 )
b101 /
1#
#25
1$
#30
0$
b10100101101001011010010110100101 "
b10100101101001011010010110100101 *
b101 %
b101 ,
0#
#35
1$
#40
0$
b10101010101010101010101010101010 (
b10101010101010101010101010101010 .
b1100 )
b1100 /
1#
#45
1$
#50
0$
b10101010101010101010101010101010 "
b10101010101010101010101010101010 *
b1100 %
b1100 ,
0#
#55
1$
#60
0$
b11111111111111111111111111111111 (
b11111111111111111111111111111111 .
b0 )
b0 /
1#
#65
1$
#70
0$
b10100101101001011010010110100101 !
b10100101101001011010010110100101 +
b101 &
b101 -
b0 "
b0 *
b0 %
b0 ,
0#
#75
1$
#80
0$
b10010001101000101011001111000 (
b10010001101000101011001111000 .
b11111 )
b11111 /
1#
#85
1$
#90
0$
b10101010101010101010101010101010 !
b10101010101010101010101010101010 +
b1100 &
b1100 -
b10010001101000101011001111000 "
b10010001101000101011001111000 *
b11111 %
b11111 ,
0#
#95
1$
#100
0$
b0 !
b0 +
b10 &
b10 -
b0 "
b0 *
b1 %
b1 ,
