PC_and_IMEN/IMEN_AND_PC/IMEN.v
// Instruction Memory
// de 32bits.
// by Alan Gomez
// 
// 1. Crea un módulo llamado IMEM con los siguientes puertos:
// input [31:0] addr → dirección de la instrucción
// output [31:0] instruction → instrucción leída
// 
// 2. Implementa la memoria como un arreglo de 16 palabras de 32 bits:
// reg [31:0] memory [0:15];
// 
// 3. Inicializa la memoria con 10 instrucciones, ejemplo:
// initial begin
// memory[0] = 32'b000000_00001_00010_00011_00000_100000; // ADD $3, $1, $2
// memory[1] = 32'b001000_01000_01001_0000000000001010; // ADDI $9, $8, 10
// ...
// ...
// ...
// end
// 
// 4. Asigna la instrucción de salida según la dirección:
// assign instruction = memory[addr[4:0]]; // usa bits menos significativos
// 
// 5. Testbench para IMEM
// Crea un testbench que recorra varias direcciones (addr) y muestre la instrucción con $display.
// Extrae los campos de la instrucción (opcode, rs, rt, rd, shamt, funct o immediate) y muéstralos en pantalla.

module IMEN( input [31:0] addr,
             output [31:0] instruction );
    reg [31:0] memory [0:15];

    initial begin
        memory[0]  = 32'b000000_00001_00010_00011_00000_100000;
        memory[1]  = 32'b001000_01000_01001_0000000000001010;
        memory[2]  = 32'b100000_00001_00010_00011_00000_100000;
        memory[3]  = 32'b010000_00001_00010_00011_00000_100000;
        memory[4]  = 32'b001000_00001_00010_00011_00000_100000;
        memory[5]  = 32'b000100_00001_00010_00011_00000_100000;
        memory[6]  = 32'b000010_00001_00010_00011_00000_100000;
        memory[7]  = 32'b000001_00001_00010_00011_00000_100000;
        memory[8]  = 32'b000000_10001_00010_00011_00000_100000;
        memory[9]  = 32'b000000_01001_00010_00011_00000_100000;
        memory[10] = 32'b000000_00101_00010_00011_00000_100000;
        memory[11] = 32'b000000_00011_00010_00011_00000_100000;
        memory[12] = 32'b000000_00000_00010_00011_00000_100000;
        memory[13] = 32'b000000_00001_10010_00011_00000_100000;
        memory[14] = 32'b000000_00001_01010_00011_00000_100000;
        memory[15] = 32'b000000_00001_00110_00011_00000_100000;
    end

    assign instruction = memory[addr[3:0]];

endmodule

// module IMEN_tb;
//     reg [31:0] addr;
//     wire [31:0] instruction;

//     IMEN uut (
//         .addr(addr),
//         .instruction(instruction)   
//     );

//     initial begin
//         $dumpfile("IMEN_tb.vcd");
//         $dumpvars(0, IMEN_tb);

//         addr = 32'd0;  #10; display_fields();
//         addr = 32'd1;  #10; display_fields();
//         addr = 32'd2;  #10; display_fields();
//         addr = 32'd3;  #10; display_fields();
//         addr = 32'd4;  #10; display_fields();
//         addr = 32'd5;  #10; display_fields();
//         addr = 32'd6;  #10; display_fields();
//         addr = 32'd7;  #10; display_fields();
//         addr = 32'd8;  #10; display_fields();
//         addr = 32'd15; #10; display_fields();

//         #10 $finish;
//     end

//     task display_fields;
//         begin
//             $display("Time=%0t | addr=%0d", $time, addr);
//             $display("Instruction = %b", instruction);
//             $display("opcode = %b | rs = %b | rt = %b | rd = %b | shamt = %b | funct/immediate = %b",
//                      instruction[31:26], instruction[25:21], instruction[20:16],
//                      instruction[15:11], instruction[10:6], instruction[5:0]);
//             $display("------------------------------------------------------");
//         end
//     endtask
// endmodule

PC_and_IMEN/IMEN_AND_PC/Program_counter.v
// Program counter
// de 32bits.
// by Alan Gomez

// Ejercicio 1: Crear el módulo PC

// 1. Crea un módulo llamado PC con los siguientes puertos:
//      input clk → reloj
//      input reset → reinicia el PC
//      input [31:0] next_pc → dirección siguiente
//      output reg [31:0] current_pc → dirección actual

// 2. El PC debe:
//      Reiniciarse a 0 cuando reset = 1.
//      Tomar el valor de next_pc en cada flanco positivo de clk.

// 3. Testbench para PC
//      Crea un testbench que:
//      Inicialice clk = 0 y reset = 1.
//      Desactive reset después de algunos ciclos.
//      Cambie next_pc cada ciclo y observe current_pc.
//      Usa $display para imprimir el valor de current_pc cada ciclo.

module PC(  
    input clk,
    input reset,
    input [31:0] next_pc,
    output reg [31:0] current_pc
);
    
    always @(posedge clk or posedge reset) begin
        if (reset)
            current_pc <= 32'b0;
        else
            current_pc <= next_pc;
    end

endmodule


// module PC_tb;

//     // Entradas
//     reg [31:0] next_pc;
//     reg clk;
//     reg reset;

//     // Salida
//     wire [31:0] current_pc;

//     // Instancia del módulo bajo prueba (DUT)
//     PC uut (
//         .clk(clk),
//         .reset(reset),
//         .next_pc(next_pc),
//         .current_pc(current_pc)
//     );

//     // Generador de reloj: cambia cada 5 ns
//     always #5 clk = ~clk;

//     initial begin
//         $dumpfile("PC_tb.vcd");
//         $dumpvars(0, PC_tb);

//         // Inicialización
//         clk = 0;
//         reset = 1;
//         next_pc = 0;

//         // Mantener reset activo por unos ciclos
//         #10 reset = 0;

//         // Cambiar next_pc en cada ciclo
//         next_pc = 32'd1; #10;
//         next_pc = 32'd2; #10;
//         next_pc = 32'd3; #10;
//         next_pc = 32'd4; #10;

//         // Mostrar resultados
//         $display("Time=%0t | next_pc=%0d | current_pc=%0d", $time, next_pc, current_pc);

//         // Terminar simulación
//         #10 $finish;
//     end

// endmodule

PC_and_IMEN/IMEN_AND_PC/PC_IMEN.v
//Alan Gomez

// Ejercicio 3: Integración PC + IMEM
// Conecta tu módulo PC con IMEM de manera que:

// current_pc del PC se use como addr de IMEM.

// Cada ciclo se lea la instrucción correspondiente.

// Crea un testbench que:

// Avance el PC automáticamente (next_pc = current_pc + 1 o +4 según convenga).

// Muestre la instrucción completa y los campos en cada ciclo.

// Ejemplo de salida esperada:

// PC=0, Instr=000000_00001_00010_00011_00000_100000
// opcode=000000 rs=00001 rt=00010 rd=00011 shamt=00000 funct=100000
// PC=1, Instr=001000_01000_01001_0000000000001010 opcode=001000 rs=01000 rt=01001 immediate=0000000000001010

// iverilog -o PC_IMEN.out PC_IMEN.v Program_counter.v IMEN.v 
// vvp PC_IMEN.out
// gtkwave tb_pc_imen.vcd

module pc_imen(
    input [31:0] PC_INPUT,
    input clk,
    input reset,
    output [31:0] instruction_OUTPUT 
);

    wire [31:0] current_pc;


    PC U1(.next_pc(PC_INPUT), .clk(clk), .reset(reset), .current_pc(current_pc));
    IMEN U2(.addr(current_pc), .instruction(instruction_OUTPUT));

endmodule



module tb_pc_imen;

    reg clk;
    reg reset;
    reg [31:0] PC_INPUT;
    wire [31:0] instruction_OUTPUT;

    pc_imen uut (
        .PC_INPUT(PC_INPUT),
        .clk(clk),
        .reset(reset),
        .instruction_OUTPUT(instruction_OUTPUT)
    );

    // Generador de reloj
    always #5 clk = ~clk;

    initial begin
        $dumpfile("tb_pc_imen.vcd");
        $dumpvars(0, tb_pc_imen);

        clk = 0;
        reset = 1;
        PC_INPUT = 0;
        #10 reset = 0;

        repeat (16) begin
            #10 display_fields();
            PC_INPUT = PC_INPUT + 1; // avanza PC
        end

        #10 $finish;
    end

    task display_fields;
        reg [5:0] opcode;
        begin
            opcode = instruction_OUTPUT[31:26];
            $display("PC=%0d | Instr=%b", PC_INPUT, instruction_OUTPUT);

            // Si opcode == 0 → tipo R
            if (opcode == 6'b000000) begin
                $display("opcode=%b rs=%b rt=%b rd=%b shamt=%b funct=%b",
                    instruction_OUTPUT[31:26],
                    instruction_OUTPUT[25:21],
                    instruction_OUTPUT[20:16],
                    instruction_OUTPUT[15:11],
                    instruction_OUTPUT[10:6],
                    instruction_OUTPUT[5:0]
                );
            end 
            // Si opcode != 0 → tipo I
            else begin
                $display("opcode=%b rs=%b rt=%b immediate=%b",
                    instruction_OUTPUT[31:26],
                    instruction_OUTPUT[25:21],
                    instruction_OUTPUT[20:16],
                    instruction_OUTPUT[15:0]
                );
            end

            $display("------------------------------------------------------");
        end
    endtask

endmodule

PC_and_IMEN/IMEN_AND_PC/tb_pc_imen.vcd
$date
	Sun Oct 12 23:47:53 2025
$end
$version
	Icarus Verilog
$end
$timescale
	1s
$end
$scope module tb_pc_imen $end
$var wire 32 ! instruction_OUTPUT [31:0] $end
$var reg 32 " PC_INPUT [31:0] $end
$var reg 1 # clk $end
$var reg 1 $ reset $end
$scope module uut $end
$var wire 32 % PC_INPUT [31:0] $end
$var wire 1 # clk $end
$var wire 1 $ reset $end
$var wire 32 & instruction_OUTPUT [31:0] $end
$var wire 32 ' current_pc [31:0] $end
$scope module U1 $end
$var wire 1 # clk $end
$var wire 32 ( next_pc [31:0] $end
$var wire 1 $ reset $end
$var reg 32 ) current_pc [31:0] $end
$upscope $end
$scope module U2 $end
$var wire 32 * addr [31:0] $end
$var wire 32 + instruction [31:0] $end
$upscope $end
$upscope $end
$scope task display_fields $end
$var reg 6 , opcode [5:0] $end
$upscope $end
$upscope $end
$enddefinitions $end
$comment Show the parameter values. $end
$dumpall
$end
#0
$dumpvars
bx ,
b1000100001100000100000 +
b0 *
b0 )
b0 (
b0 '
b1000100001100000100000 &
b0 %
1$
0#
b0 "
b1000100001100000100000 !
$end
#5
1#
#10
0#
0$
#15
1#
#20
0#
b1 "
b1 %
b1 (
b0 ,
#25
b100001000010010000000000001010 !
b100001000010010000000000001010 &
b100001000010010000000000001010 +
b1 '
b1 )
b1 *
1#
#30
0#
b10 "
b10 %
b10 (
b1000 ,
#35
b10000000001000100001100000100000 !
b10000000001000100001100000100000 &
b10000000001000100001100000100000 +
b10 '
b10 )
b10 *
1#
#40
0#
b11 "
b11 %
b11 (
b100000 ,
#45
b1000000001000100001100000100000 !
b1000000001000100001100000100000 &
b1000000001000100001100000100000 +
b11 '
b11 )
b11 *
1#
#50
0#
b100 "
b100 %
b100 (
b10000 ,
#55
b100000001000100001100000100000 !
b100000001000100001100000100000 &
b100000001000100001100000100000 +
b100 '
b100 )
b100 *
1#
#60
0#
b101 "
b101 %
b101 (
b1000 ,
#65
b10000001000100001100000100000 !
b10000001000100001100000100000 &
b10000001000100001100000100000 +
b101 '
b101 )
b101 *
1#
#70
0#
b110 "
b110 %
b110 (
b100 ,
#75
b1000001000100001100000100000 !
b1000001000100001100000100000 &
b1000001000100001100000100000 +
b110 '
b110 )
b110 *
1#
#80
0#
b111 "
b111 %
b111 (
b10 ,
#85
b100001000100001100000100000 !
b100001000100001100000100000 &
b100001000100001100000100000 +
b111 '
b111 )
b111 *
1#
#90
0#
b1000 "
b1000 %
b1000 (
b1 ,
#95
b10001000100001100000100000 !
b10001000100001100000100000 &
b10001000100001100000100000 +
b1000 '
b1000 )
b1000 *
1#
#100
0#
b1001 "
b1001 %
b1001 (
b0 ,
#105
b1001000100001100000100000 !
b1001000100001100000100000 &
b1001000100001100000100000 +
b1001 '
b1001 )
b1001 *
1#
#110
0#
b1010 "
b1010 %
b1010 (
#115
b101000100001100000100000 !
b101000100001100000100000 &
b101000100001100000100000 +
b1010 '
b1010 )
b1010 *
1#
#120
0#
b1011 "
b1011 %
b1011 (
#125
b11000100001100000100000 !
b11000100001100000100000 &
b11000100001100000100000 +
b1011 '
b1011 )
b1011 *
1#
#130
0#
b1100 "
b1100 %
b1100 (
#135
b100001100000100000 !
b100001100000100000 &
b100001100000100000 +
b1100 '
b1100 )
b1100 *
1#
#140
0#
b1101 "
b1101 %
b1101 (
#145
b1100100001100000100000 !
b1100100001100000100000 &
b1100100001100000100000 +
b1101 '
b1101 )
b1101 *
1#
#150
0#
b1110 "
b1110 %
b1110 (
#155
b1010100001100000100000 !
b1010100001100000100000 &
b1010100001100000100000 +
b1110 '
b1110 )
b1110 *
1#
#160
0#
b1111 "
b1111 %
b1111 (
#165
b1001100001100000100000 !
b1001100001100000100000 &
b1001100001100000100000 +
b1111 '
b1111 )
b1111 *
1#
#170
0#
b10000 "
b10000 %
b10000 (
#175
b1000100001100000100000 !
b1000100001100000100000 &
b1000100001100000100000 +
b10000 '
b10000 )
b10000 *
1#
