Control_Unit_&_ALU/ALU.v
// ALU
// Universidad del Valle de Guatemala
// Curso: Arquitectura de Computadores
// Autor: Samuel Tortola - 22094, Alan Gomez - 22115
// Fecha: 27/10/2025

//El ALU (Unidad Aritmético Lógica) es un componente fundamental del procesador que realiza operaciones aritméticas 
//y lógicas sobre los datos.

module ALU (
    input [31:0] src1,  // Primer operando
    input [31:0] src2,    // Segundo operando
    input [3:0] alu_control,  // Señal de control para seleccionar la operación de la ALU
    output reg [31:0] result, // Resultado de la operación
    output reg zero    // Señal que indica si el resultado es cero
);

    always @(*) begin
        case (alu_control)
            4'b0010: result = src1 + src2; // suma
            4'b0110: result = src1 - src2; // resta
            4'b1000: result = src1 * src2; // Multiplicación
            4'b1001: result = src1 / src2; // división
            default: result = 32'b0; // Operación por defecto
        endcase

        // Establecer la señal zero si el resultado es cero
        if (result == 32'b0)
            zero = 1;
        else
            zero = 0;


    end



    endmodule

Control_Unit_&_ALU/Testbench_ALU.v
module testbench_ALU;

// ================================================
// 1. DECLARACIÓN DE SEÑALES
// ================================================
// Señales para conectar al DUT (Design Under Test)
    reg  [31:0] src1;
    reg  [31:0] src2;
    reg  [3:0] alu_control;
    wire [31:0] result;
    wire zero;

    // ================================================
    // 2. INSTANCIACIÓN DEL DISEÑO BAJO PRUEBA (DUT)
    // ================================================

    ALU dut (
        .src1(src1),
        .src2(src2),
        .alu_control(alu_control),
        .result(result),
        .zero(zero)
    );


    // ================================================
    // 3. GENERACIÓN DE ESTÍMULOS Y MONITOREO
    // ================================================

    initial begin
        // Inicialización de señales
        src1 = 32'd0;
        src2 = 32'd0;
        alu_control = 4'b0000;
       

        #10;
        src1 = 32'd15; // Primer operando
        src2 = 32'd5;  // Segundo operando
        alu_control = 4'b0010; // Operación de suma
        $display("Src1 - Src2 - ALU_Control - Result - Zero");
        $monitor("%0d - %0d - %b - %0d - %0b", src1, src2, alu_control, result, zero);
        $display("");

        // Esperar un tiempo y cambiar la operación para probar diferentes casos
        #10;
        alu_control = 4'b0110; // Operación de resta
        $monitor("%0d - %0d - %b - %0d - %0b", src1, src2, alu_control, result, zero);
        $display("");

        #10;
        alu_control = 4'b1000; // Operación de multiplicación
        $monitor("%0d - %0d - %b - %0d - %0b", src1, src2, alu_control, result, zero);
        $display("");

        #10;
        alu_control = 4'b1001; // Operación de división
        $monitor("%0d - %0d - %b - %0d - %0b", src1, src2, alu_control, result, zero);
        $display("");

        #10;
        alu_control = 4'b0000; // Operación por defecto
        $monitor("%0d - %0d - %b - %0d - %0b", src1, src2, alu_control, result, zero);
        $display("");

            //Cambiar operandos para probar más casos
        #10;
        src1 = 32'd20;
        src2 = 32'd4;
        alu_control = 4'b0110; // Operación de resta
        $monitor("%0d - %0d - %b - %0d - %0b", src1, src2, alu_control, result, zero);
        $display("");


        #10;
        alu_control = 4'b0010; // Operación de suma
        $monitor("%0d - %0d - %b - %0d - %0b", src1, src2, alu_control, result, zero);
        $display("");


        //Probar bandera zero
        #10;
        src1 = 32'd10;
        src2 = 32'd10;
        alu_control = 4'b0110; // Operación de resta    
        $monitor("%0d - %0d - %b - %0d - %0b", src1, src2, alu_control, result, zero);
        $display("");


        // Finalizar la simulación después de un tiempo
        #10;
        $finish;
    end


    initial begin
    $dumpfile("ALU.vcd");
    $dumpvars(0, testbench_ALU);
    end




endmodule

Control_Unit_&_ALU/ALU.vcd
$date
	Mon Oct 27 15:11:00 2025
$end
$version
	Icarus Verilog
$end
$timescale
	1s
$end
$scope module testbench_ALU $end
$var wire 1 ! zero $end
$var wire 32 " result [31:0] $end
$var reg 4 # alu_control [3:0] $end
$var reg 32 $ src1 [31:0] $end
$var reg 32 % src2 [31:0] $end
$scope module dut $end
$var wire 4 & alu_control [3:0] $end
$var wire 32 ' src1 [31:0] $end
$var wire 32 ( src2 [31:0] $end
$var reg 32 ) result [31:0] $end
$var reg 1 ! zero $end
$upscope $end
$upscope $end
$enddefinitions $end
$comment Show the parameter values. $end
$dumpall
$end
#0
$dumpvars
b0 )
b0 (
b0 '
b0 &
b0 %
b0 $
b0 #
b0 "
1!
$end
#10
0!
b10100 "
b10100 )
b10 #
b10 &
b101 %
b101 (
b1111 $
b1111 '
#20
b1010 "
b1010 )
b110 #
b110 &
#30
b1001011 "
b1001011 )
b1000 #
b1000 &
#40
b11 "
b11 )
b1001 #
b1001 &
#50
1!
b0 "
b0 )
b0 #
b0 &
#60
0!
b10000 "
b10000 )
b110 #
b110 &
b100 %
b100 (
b10100 $
b10100 '
#70
b11000 "
b11000 )
b10 #
b10 &
#80
1!
b0 "
b0 )
b110 #
b110 &
b1010 %
b1010 (
b1010 $
b1010 '
